{
  "curve": "Curve",
  "convex-finance": "Convex Finance",
  "makerdao": "MakerDAO",
  "aave": "AAVE",
  "polygon-bridge-&-staking": "Polygon Bridge & Staking",
  "wbtc": "WBTC",
  "instadapp": "Instadapp",
  "lido": "Lido",
  "anchor": "Anchor",
  "compound": "Compound",
  "uniswap": "Uniswap",
  "multichain": "Multichain",
  "abracadabra": "Abracadabra",
  "yearn-finance": "Yearn Finance",
  "sushiswap": "SushiSwap",
  "pancakeswap": "PancakeSwap",
  "balancer": "Balancer",
  "cream-finance": "CREAM Finance",
  "liquity": "Liquity",
  "venus": "Venus",
  "trader-joe": "Trader Joe",
  "hbtc": "hBTC",
  "justlend": "JustLend",
  "benqi": "Benqi",
  "frax": "Frax",
  "bancor": "Bancor",
  "mdex": "MDEX",
  "justcryptos": "JustCryptos",
  "sunswap": "SUNSwap",
  "alchemix": "Alchemix",
  "raydium": "Raydium",
  "synthetix": "Synthetix",
  "flexa": "Flexa",
  "vvs-finance": "VVS Finance",
  "juststables": "JustStables",
  "marinade-finance": "Marinade Finance",
  "beefy-finance": "Beefy Finance",
  "osmosis": "Osmosis",
  "klayswap": "KlaySwap",
  "renvm": "RenVM",
  "spookyswap": "SpookySwap",
  "synapse": "Synapse",
  "dydx": "dYdX",
  "astroport": "Astroport",
  "stacks-staking": "Stacks Staking",
  "tranchess": "Tranchess",
  "mirror": "Mirror",
  "tokemak": "Tokemak",
  "serum": "Serum",
  "katana-dex": "Katana DEX",
  "xdai-stake-bridge": "xDAI Stake Bridge",
  "badger-dao": "Badger DAO",
  "alpha-finance": "Alpha Finance",
  "truefi": "TrueFi",
  "terraswap": "Terraswap",
  "rari-capital": "Rari Capital",
  "maiar-exchange": "Maiar Exchange",
  "defi-kingdoms": "Defi Kingdoms",
  "quarry": "Quarry",
  "alpaca-finance": "Alpaca Finance",
  "neutrino": "Neutrino",
  "quickswap": "Quickswap",
  "fei-protocol": "Fei Protocol",
  "wonderland": "Wonderland",
  "geist-finance": "Geist Finance",
  "tulip-protocol": "Tulip Protocol",
  "saber": "Saber",
  "sun.io": "SUN.io",
  "biswap": "BiSwap",
  "keep3r-network": "Keep3r Network",
  "defisaver": "DefiSaver",
  "solend": "Solend",
  "atrix": "Atrix",
  "ellipsis-finance": "Ellipsis Finance",
  "armor": "Armor",
  "mento": "Mento",
  "orca": "Orca",
  "maple": "Maple",
  "tornado-cash": "Tornado Cash",
  "notional": "Notional",
  "allbridge": "Allbridge",
  "nexus-mutual": "Nexus Mutual",
  "scream": "Scream",
  "sablier-finance": "Sablier Finance",
  "yield-yak": "Yield Yak",
  "loopring": "Loopring",
  "mars-ecosystem": "Mars Ecosystem",
  "trisolaris": "Trisolaris",
  "sunny": "Sunny",
  "stader": "Stader",
  "defichain-dex": "DefiChain DEX",
  "stakedao": "StakeDAO",
  "kava": "Kava",
  "coinwind": "Coinwind",
  "chainport": "ChainPort",
  "almond": "Almond",
  "vires-finance": "Vires Finance",
  "rocket-pool": "Rocket Pool",
  "set-protocol": "Set Protocol",
  "shibaswap": "ShibaSwap",
  "pando": "Pando",
  "olympus-dao": "Olympus DAO",
  "francium": "Francium",
  "belt-finance": "Belt Finance",
  "autofarm": "Autofarm",
  "ysl.io": "YSL.IO",
  "index-coop": "Index Coop",
  "origin-dollar": "Origin Dollar",
  "pylon-protocol": "Pylon Protocol",
  "ribbon-finance": "Ribbon Finance",
  "pangolin": "Pangolin",
  "defidollar-dao": "DefiDollar DAO",
  "dodo": "DODO",
  "harvest-finance": "Harvest Finance",
  "spiritswap": "SpiritSwap",
  "apeswap": "ApeSwap",
  "blizz-finance": "Blizz Finance",
  "angle": "Angle",
  "stakehound": "StakeHound",
  "keeperdao": "KeeperDAO",
  "dforce": "dForce",
  "tectonic": "Tectonic",
  "defichain-loans": "DefiChain Loans",
  "element-finance": "Element Finance",
  "keep-network": "KEEP Network",
  "thorchain": "Thorchain",
  "opyn": "Opyn",
  "reflexer": "Reflexer",
  "mochifi": "MochiFi",
  "hundred-finance": "Hundred Finance",
  "ankr": "Ankr",
  "saddle-finance": "Saddle Finance",
  "apricot-finance": "Apricot Finance",
  "reaper-farm": "Reaper Farm",
  "bunny": "Bunny",
  "kava-lend": "Kava Lend",
  "waves-exchange": "Waves Exchange",
  "b.protocol": "B.Protocol",
  "g-uni": "G-UNI",
  "vesper": "Vesper",
  "qidao": "QiDao",
  "tarot": "Tarot",
  "lightning-network": "Lightning Network",
  "larix": "Larix",
  "beethoven-x": "Beethoven X",
  "solo-top": "Solo Top",
  "wrapped-bnb": "Wrapped BNB",
  "mm-finance": "MM Finance",
  "stakewise": "StakeWise",
  "pnetwork": "pNetwork",
  "mstable": "mStable",
  "hop-protocol": "Hop Protocol",
  "acryptos": "ACryptoS",
  "klima-dao": "Klima DAO",
  "spectrum-protocol": "Spectrum Protocol",
  "gmx": "GMX",
  "aldrin": "Aldrin",
  "bxh": "BXH",
  "cbridge": "cBridge",
  "port-finance": "Port Finance",
  "qubit": "Qubit",
  "inverse-finance": "Inverse Finance",
  "jpool": "JPool",
  "o3-swap": "O3 Swap",
  "hector-dao": "Hector DAO",
  "enzyme-finance": "Enzyme Finance",
  "filda": "FilDA",
  "uma-protocol": "UMA Protocol",
  "superfluid": "Superfluid",
  "zkswap": "ZKSwap",
  "liquid-driver": "Liquid Driver",
  "yokaiswap": "YokaiSwap",
  "sovryn": "Sovryn",
  "idle-finance": "Idle Finance",
  "mantra-dao": "MANTRA DAO",
  "socean": "Socean",
  "lyra": "Lyra",
  "friktion": "Friktion",
  "ondo-finance": "Ondo Finance",
  "ramp": "Ramp",
  "ooki": "Ooki",
  "parrot-protocol": "Parrot Protocol",
  "channels-finance": "Channels Finance",
  "flamincome": "Flamincome",
  "market": "Market",
  "ref-finance": "Ref Finance",
  "wannaswap": "WannaSwap",
  "tranquil-finance": "Tranquil Finance",
  "position-exchange": "Position Exchange",
  "mango-markets": "Mango Markets",
  "unslashed": "Unslashed",
  "eosauthority-rex": "EOSAuthority REX",
  "pickle": "Pickle",
  "dopex": "Dopex",
  "metronome": "Metronome",
  "cronaswap": "CronaSwap",
  "kronos-dao": "Kronos DAO",
  "kyber": "Kyber",
  "planet-finance": "Planet Finance",
  "pooltogether": "PoolTogether",
  "balanced": "Balanced",
  "invictusdao": "InvictusDAO",
  "deversifi": "DeversiFi",
  "defibox": "DefiBox",
  "oolongswap": "OolongSwap",
  "mercurial-finance": "Mercurial Finance",
  "moola-market": "Moola Market",
  "injective-protocol": "Injective Protocol",
  "spartacus": "Spartacus",
  "stafi": "Stafi",
  "zenlink": "Zenlink",
  "dfyn-network": "Dfyn Network",
  "apollodao": "ApolloDAO",
  "solarbeam": "Solarbeam",
  "derivadex": "DerivaDEX",
  "wing-finance": "Wing Finance",
  "sifchain": "Sifchain",
  "yoshi-exchange": "Yoshi Exchange",
  "secret-network": "Secret Network",
  "boringdao": "BoringDAO",
  "secret-bridge": "Secret Bridge",
  "tinlake": "Tinlake",
  "orion-money": "Orion Money",
  "88mph": "88mph",
  "enterdao": "EnterDAO",
  "autoshark": "AutoShark",
  "viperswap": "ViperSwap",
  "defrost": "Defrost",
  "yieldly": "Yieldly",
  "wepiggy": "WePiggy",
  "nexus-protocol": "Nexus Protocol",
  "liqee": "Liqee",
  "annex": "Annex",
  "gro": "Gro",
  "penguin-finance": "Penguin Finance",
  "sharedstake": "SharedStake",
  "atlantis-loans": "Atlantis Loans",
  "dinoswap": "DinoSwap",
  "knightswap-finance": "KnightSwap Finance",
  "bao-finance": "Bao Finance",
  "redacted-cartel": "Redacted Cartel",
  "netswap": "NetSwap",
  "lendhub": "LendHub",
  "defi-swap": "Defi Swap",
  "ubeswap": "Ubeswap",
  "omm": "Omm",
  "loop-finance": "Loop Finance",
  "composable-finance": "Composable Finance",
  "popsicle-finance": "Popsicle Finance",
  "bakeryswap": "BakerySwap",
  "secretswap": "SecretSwap",
  "beta-finance": "Beta Finance",
  "snowball": "Snowball",
  "leaguedao": "LeagueDAO",
  "stellarx": "StellarX",
  "onx-finance": "OnX Finance",
  "pala": "Pala",
  "goldfinch": "Goldfinch",
  "donkey": "Donkey",
  "thetanuts": "ThetaNuts",
  "mojitoswap": "MojitoSwap",
  "psyoptions": "PsyOptions",
  "moneyonchain": "MoneyOnChain",
  "euphoria": "Euphoria",
  "insurace": "InsurAce",
  "youves": "Youves",
  "impermax-finance": "Impermax Finance",
  "pstake": "pStake",
  "auroraswap": "AuroraSwap",
  "romedao": "RomeDAO",
  "wagyuswap": "WagyuSwap",
  "meta-pool": "Meta Pool",
  "pendle": "Pendle",
  "definix": "Definix",
  "revest-finance": "Revest Finance",
  "katana": "Katana",
  "bifi": "BiFi",
  "beanstalk": "Beanstalk",
  "cashio": "Cashio",
  "arrow": "Arrow",
  "1inch-network": "1inch Network",
  "pacoca": "Pacoca",
  "chainge-finance": "Chainge Finance",
  "squiddao": "SquidDao",
  "mars-poolin": "Mars Poolin",
  "cherryswap": "CherrySwap",
  "temple-dao": "Temple DAO",
  "tetu": "Tetu",
  "snowbank": "Snowbank",
  "polkaswap": "Polkaswap",
  "synthetify": "Synthetify",
  "wanswap-dex": "WanSwap Dex",
  "moonpot": "Moonpot",
  "sherlock": "Sherlock",
  "ton-swap": "TON Swap",
  "aladdin-dao": "Aladdin DAO",
  "wrapped": "Wrapped",
  "euler": "Euler",
  "realt": "RealT",
  "kava-swap": "Kava Swap",
  "bella-protocol": "Bella Protocol",
  "vexchange": "Vexchange",
  "reserve": "Reserve",
  "zookeeper": "Zookeeper",
  "yield-protocol": "Yield Protocol",
  "algofi": "Algofi",
  "rabbit-finance": "Rabbit Finance",
  "babylon-finance": "Babylon Finance",
  "yaxis": "yAxis",
  "strike": "Strike",
  "swop": "Swop",
  "mimo-defi": "Mimo Defi",
  "karura-swap": "Karura Swap",
  "zilswap": "ZilSwap",
  "mcdex": "MCDEX",
  "mm-optimizer": "MM Optimizer",
  "ten-finance": "TEN Finance",
  "ichi-farm": "ICHI Farm",
  "axial": "Axial",
  "orion-protocol": "Orion Protocol",
  "connext": "Connext",
  "karura-dollar-(kusd)": "Karura Dollar (kUSD)",
  "perpetual-protocol": "Perpetual Protocol",
  "chargedefi": "ChargeDeFi",
  "fodl-finance": "FODL Finance",
  "premia": "Premia",
  "imtoken": "imToken",
  "apy-finance": "APY Finance",
  "jet": "Jet",
  "clipper": "Clipper",
  "metaversepro": "Metaversepro",
  "jswap": "JSwap",
  "kaidex": "Kaidex",
  "revault": "Revault",
  "gnosis": "Gnosis",
  "ecurve": "eCurve",
  "across": "Across",
  "linear-finance": "Linear Finance",
  "ocp-finance": "OCP Finance",
  "unicly": "Unicly",
  "barnbridge": "BarnBridge",
  "tethys-finance": "Tethys Finance",
  "fortube": "ForTube",
  "boofinance": "BooFinance",
  "flux-protocol": "Flux Protocol",
  "flarex": "FlareX",
  "starterra": "Starterra",
  "dhedge": "dHEDGE",
  "moonfarm": "MoonFarm",
  "aavegotchi": "Aavegotchi",
  "sheepdex": "SheepDex",
  "robo-vault": "Robo-Vault",
  "guard(helmet)": "Guard(Helmet)",
  "karura-liquid-staking": "Karura Liquid-Staking",
  "lumenswap": "LumenSwap",
  "powerpool": "PowerPool",
  "valuedefi": "ValueDefi",
  "tezos-liquidity-baking": "Tezos Liquidity Baking",
  "swapr": "Swapr",
  "fusefi": "FuseFi",
  "jetfuel-finance": "JetFuel Finance",
  "unagii": "Unagii",
  "rose": "Rose",
  "tracer": "Tracer",
  "shell-protocol": "Shell Protocol",
  "gamma": "Gamma",
  "grim-finance": "Grim Finance",
  "cardstarter": "Cardstarter",
  "dfx-finance": "DFX Finance",
  "ouchi-finance": "Ouchi Finance",
  "nftb": "NFTb",
  "nerve-network": "Nerve Network",
  "topshelf": "TopShelf",
  "idex": "IDEX",
  "arkadiko": "Arkadiko",
  "maximizer": "Maximizer",
  "bridge-mutual": "Bridge Mutual",
  "fortress": "Fortress",
  "dinosaur-eggs": "Dinosaur Eggs",
  "socialswap": "SocialSwap",
  "benswap": "BenSwap",
  "ethernity-chain": "Ethernity Chain",
  "mistswap": "MistSwap",
  "unit-protocol": "Unit Protocol",
  "xtoken": "xToken",
  "jade-protocol": "Jade Protocol",
  "kogefarm": "Kogefarm",
  "papa-dao": "Papa DAO",
  "flare-loans": "Flare Loans",
  "nearpad": "Nearpad",
  "kolibri": "Kolibri",
  "hegic": "Hegic",
  "elk": "Elk",
  "fantohm": "Fantohm",
  "alchemist": "Alchemist",
  "zoocoin": "ZooCoin",
  "alkemi": "Alkemi",
  "cryptex": "Cryptex",
  "nemesis-dao": "Nemesis DAO",
  "nftx": "NFTX",
  "perlin": "Perlin",
  "btcst": "BTCST",
  "macaronswap": "MacaronSwap",
  "swamp-finance": "Swamp Finance",
  "piedao": "PieDAO",
  "jetswap": "JetSwap",
  "galaxygoogle-dao": "GalaxyGoogle DAO",
  "fractional-art": "Fractional Art",
  "energiswap": "Energiswap",
  "magnet-dao": "Magnet DAO",
  "demeter": "Demeter",
  "platypus-finance": "Platypus Finance",
  "opium": "Opium",
  "mimas-finance": "Mimas Finance",
  "crodex": "Crodex",
  "hakka-finance": "Hakka Finance",
  "huckleberry": "Huckleberry",
  "adamant-finance": "Adamant Finance",
  "knit-finance": "Knit Finance",
  "unifarm": "UniFarm",
  "ola-finance": "Ola Finance",
  "honeyswap": "Honeyswap",
  "cashcow-finance": "CashCow Finance",
  "charm-finance": "Charm Finance",
  "jarvis-network": "Jarvis Network",
  "kalata": "Kalata",
  "kine-finance": "Kine Finance",
  "indexed-finance": "Indexed Finance",
  "integral": "Integral",
  "thorusfi": "ThorusFi",
  "wault": "Wault",
  "bumper-finance": "Bumper Finance",
  "gibxswap": "GIBXSwap",
  "chest-finance": "Chest Finance",
  "chfry-finance": "CHFRY Finance",
  "complifi": "CompliFi",
  "makiswap": "MakiSwap",
  "thorstarter": "Thorstarter",
  "aztec": "Aztec",
  "erasure": "Erasure",
  "wasabix": "Wasabix",
  "tidal-finance": "Tidal Finance",
  "plenty-defi": "Plenty Defi",
  "geyser": "Geyser",
  "vaporwave": "Vaporwave",
  "latteswap": "LatteSwap",
  "back-finance": "Back Finance",
  "quipuswap": "QuipuSwap",
  "itrust-finance": "iTrust Finance",
  "teddy-cash": "Teddy Cash",
  "pippi": "Pippi",
  "tranche-finance": "Tranche Finance",
  "defis-network": "DeFis Network",
  "creamswap": "CreamSwap",
  "cometh": "Cometh",
  "growth-defi": "Growth DeFi",
  "smoothy": "Smoothy",
  "niifi": "NiiFi",
  "stakesteak": "StakeSteak",
  "eleven-finance": "Eleven Finance",
  "ddex": "DDEX",
  "oxygen": "Oxygen",
  "alita-finance": "Alita Finance",
  "flamingo-finance": "Flamingo Finance",
  "kuswap": "KuSwap",
  "wrap-protocol": "Wrap Protocol",
  "luaswap": "LuaSwap",
  "farmersonly": "FarmersOnly",
  "tempus-finance": "Tempus Finance",
  "mushrooms-finance": "Mushrooms Finance",
  "gearbox": "Gearbox",
  "wheat-protocol": "Wheat Protocol",
  "paint-swap": "Paint Swap",
  "pole-aggregator": "Pole Aggregator",
  "marginswap": "MarginSwap",
  "soy-finance": "Soy Finance",
  "cozy-finance": "Cozy Finance",
  "iron-finance": "Iron Finance",
  "paladin-finance": "Paladin Finance",
  "anchorswap": "AnchorSwap",
  "crystl-finance": "Crystl Finance",
  "fiat-dao": "FIAT DAO",
  "cyclone": "Cyclone",
  "openocean": "OpenOcean",
  "depth": "Depth",
  "ifpool": "IFPool",
  "orcadao": "OrcaDAO",
  "golff-protocol": "Golff Protocol",
  "unfederalreserve": "unFederalReserve",
  "vee-finance": "Vee Finance",
  "universe-finance": "Universe Finance",
  "empiredex": "EmpireDEX",
  "float-protocol": "Float Protocol",
  "hurricaneswap": "HurricaneSwap",
  "drift": "Drift",
  "umami-finance": "Umami Finance",
  "universe-xyz": "Universe XYZ",
  "lobis": "Lobis",
  "sashimiswap": "SashimiSwap",
  "pilot-protocol": "Pilot Protocol",
  "warp-protocol": "Warp Protocol",
  "ttswap": "TTswap",
  "tesseract": "Tesseract",
  "life-dao": "Life DAO",
  "tokenlon": "Tokenlon",
  "kswap-finance": "KSwap Finance",
  "stonedefi": "StoneDefi",
  "atlas-usv": "Atlas USV",
  "goose-finance": "Goose Finance",
  "defiplaza": "DefiPlaza",
  "ice-dao": "Ice DAO",
  "summit-defi": "Summit Defi",
  "deri-protocol": "Deri Protocol",
  "exinswap": "ExinSwap",
  "lootswap": "LootSwap",
  "mooniswap": "MooniSwap",
  "niob-finance": "Niob Finance",
  "yogi-finance": "Yogi Finance",
  "umbria-network": "Umbria Network",
  "wingswap": "WingSwap",
  "nerve": "Nerve",
  "mint-club": "Mint Club",
  "cook-finance": "Cook Finance",
  "cub-finance": "Cub Finance",
  "soulswap": "SoulSwap",
  "lydia": "Lydia",
  "wagmidao": "WagmiDAO",
  "polycat": "Polycat",
  "glide-finance": "Glide Finance",
  "carbonswap": "CarbonSwap",
  "ocean-protocol": "Ocean Protocol",
  "oh-finance": "Oh Finance",
  "scientix": "Scientix",
  "tangoswap": "TangoSwap",
  "pantherswap": "PantherSwap",
  "genshiro": "Genshiro",
  "cycle-finance": "Cycle Finance",
  "furucombo": "Furucombo",
  "bscswap": "BSCSwap",
  "bearn": "Bearn",
  "firebird": "Firebird",
  "cap": "Cap",
  "beglobal-finance": "BeGlobal Finance",
  "trava-finance": "Trava Finance",
  "magic-land": "Magic Land",
  "gyro": "Gyro",
  "defily": "Defily",
  "pizza": "Pizza",
  "unilend": "Unilend",
  "convergence": "Convergence",
  "bishares": "BiShares",
  "templar-dao": "Templar DAO",
  "cvi-finance": "CVI Finance",
  "polyquity": "PolyQuity",
  "fabric": "Fabric",
  "whiteheart": "Whiteheart",
  "drops": "Drops",
  "basketdao": "BasketDAO",
  "crow-finance": "Crow Finance",
  "swipe": "Swipe",
  "polymarket": "Polymarket",
  "liquidrium": "Liquidrium",
  "oneswap": "OneSwap",
  "crunchy-network": "Crunchy Network",
  "cvault-finance": "cVault Finance",
  "pidao-finance": "Pidao Finance",
  "tropical-finance": "Tropical Finance",
  "nsure": "Nsure",
  "augur": "Augur",
  "ink-protocol": "INK Protocol",
  "otterclam": "OtterClam",
  "everrise": "EverRise",
  "agave": "Agave",
  "fuzz-finance": "Fuzz Finance",
  "potluck-protocol": "Potluck Protocol",
  "bscstation": "BSCStation",
  "necc": "Necc",
  "wardenswap": "WardenSwap",
  "cafeswap": "CafeSwap",
  "oakfarm": "OakFarm",
  "gains-network": "Gains Network",
  "openswap": "OpenSwap",
  "hyperswap": "HyperSwap",
  "symmetric": "Symmetric",
  "timewarp": "Timewarp",
  "swerve": "Swerve",
  "snowswap": "SnowSwap",
  "siren": "Siren",
  "rocketswap": "RocketSwap",
  "leonicornswap": "LeonicornSwap",
  "pods-finance": "Pods Finance",
  "defyswap": "DefySwap",
  "naos-finance": "NAOS Finance",
  "lixir-finance": "Lixir Finance",
  "standard-protocol": "Standard Protocol",
  "cheesedao": "CheeseDAO",
  "avaware": "Avaware",
  "poof-cash": "Poof Cash",
  "arbis-finance": "Arbi's Finance",
  "piggybank-dao": "Piggybank DAO",
  "muesliswap": "MuesliSwap",
  "handle-fi": "Handle Fi",
  "kaco-finance": "KACO Finance",
  "matrix-farm": "Matrix Farm",
  "midasdao": "MidasDAO",
  "feeder-finance": "Feeder Finance",
  "asol": "aSOL",
  "apwine": "APWine",
  "yam-finance": "Yam Finance",
  "exodia": "Exodia",
  "shibance": "Shibance",
  "openleverage": "OpenLeverage",
  "padswap": "PadSwap",
  "fuji-dao": "Fuji DAO",
  "nft20": "NFT20",
  "mobius-money": "Mobius Money",
  "stabilize": "Stabilize",
  "unore": "UnoRe",
  "becoswap": "BecoSwap",
  "morpheus-swap": "Morpheus Swap",
  "kafe-finance": "Kafe Finance",
  "multiplier": "Multiplier",
  "sencha": "Sencha",
  "volmex": "Volmex",
  "hunny-finance": "Hunny Finance",
  "rubicon": "Rubicon",
  "layer2-finance": "Layer2 Finance",
  "pop-town": "Pop Town",
  "ester-finance": "Ester Finance",
  "yetiswap": "YetiSwap",
  "unifi": "UniFi",
  "definer": "DeFiner",
  "evolutionland": "EvolutionLand",
  "hyper-finance": "Hyper Finance",
  "photonswap-finance": "PhotonSwap Finance",
  "xsigma": "xSigma",
  "bondappetit": "BondAppetit",
  "pandaswap": "PandaSwap",
  "telos-swap": "Telos Swap",
  "swift-finance": "Swift Finance",
  "spicyswap": "SpicySwap",
  "youswap": "YouSwap",
  "ergodex": "ErgoDEX",
  "klend": "KLend",
  "onedao-finance": "OneDAO Finance",
  "amun-tokens": "Amun Tokens",
  "duckydefi": "DuckyDeFi",
  "embr-finance": "Embr Finance",
  "polly-finance": "Polly Finance",
  "big-data-protocol": "Big Data Protocol",
  "metareserve": "MetaReserve",
  "soda-protocol": "Soda Protocol",
  "sentre": "Sentre",
  "allinx": "Allinx",
  "xdefi": "XDeFi",
  "globiance": "Globiance",
  "bagels-finance": "Bagels Finance",
  "yfii": "YFII",
  "solyard": "Solyard",
  "safeswap": "SafeSwap",
  "hades-swap": "Hades Swap",
  "upfi-network": "UPFI Network",
  "swapperchan": "SwapperChan",
  "vigor": "Vigor",
  "olive-cash": "Olive Cash",
  "klondike-finance": "Klondike Finance",
  "percent-finance": "Percent Finance",
  "waterloan": "WaterLoan",
  "seadex": "SeaDex",
  "cobraswap": "CobraSwap",
  "component": "Component",
  "phoenix-finance": "Phoenix Finance",
  "o2-dao": "O2 DAO",
  "lien": "Lien",
  "strudel-finance": "Strudel Finance",
  "pinkswap": "PinkSwap",
  "dios-finance": "Dios Finance",
  "ram-protocol": "Ram Protocol",
  "trick-or-treat-farm": "Trick or Treat Farm",
  "float-capital": "Float Capital",
  "unitrade": "UniTrade",
  "canary": "Canary",
  "shinobi": "Shinobi",
  "powerbomb-finance": "Powerbomb Finance",
  "forcedao": "ForceDAO",
  "polydex": "Polydex",
  "bossswap": "BossSwap",
  "waka-finance": "Waka Finance",
  "sakeperp": "SakePerp",
  "rskswap": "RskSwap",
  "1swap": "1Swap",
  "shield": "Shield",
  "miningtycoon": "MiningTycoon",
  "singular-farm": "Singular Farm",
  "oddz": "Oddz",
  "cover-protocol": "Cover Protocol",
  "unusdao": "UnusDao",
  "0.exchange": "0.exchange",
  "arbinyan": "ArbiNYAN",
  "witswap": "WitSwap",
  "baguette": "Baguette",
  "peakdefi": "PEAKDEFI",
  "nileriver": "Nileriver",
  "suterusu": "Suterusu",
  "chronoswap": "Chronoswap",
  "bnbminer-finance": "BNBMiner Finance",
  "multi-chain-miner": "Multi-Chain Miner",
  "vikingsfinance": "VikingsFinance",
  "varen": "Varen",
  "steakbank-finance": "SteakBank Finance",
  "bunnypark": "BunnyPark",
  "mobius-finance": "Mobius Finance",
  "augmented-finance": "Augmented Finance",
  "wild-credit": "Wild Credit",
  "zencha-finance": "Zencha Finance",
  "newdex": "NewDex",
  "augury-finance": "Augury Finance",
  "xenophon": "Xenophon",
  "xeus": "XEUS",
  "hfione": "HFIone",
  "artemis-protocol": "Artemis Protocol",
  "auctus": "Auctus",
  "superfarm": "SuperFarm",
  "seeder-finance": "Seeder Finance",
  "mochiswap": "MochiSwap",
  "swarm-markets": "Swarm Markets",
  "halodao": "HaloDAO",
  "ideamarket": "Ideamarket",
  "newland": "Newland",
  "serum-swap": "Serum Swap",
  "futureswap": "FutureSwap",
  "dopple-finance": "Dopple Finance",
  "unipower": "UniPower",
  "cashcow-protocol": "CashCow Protocol",
  "obswap": "OBSwap",
  "dev-protocol": "Dev Protocol",
  "domani-protocol": "Domani Protocol",
  "kwikswap": "KwikSwap",
  "luxor-money": "Luxor Money",
  "arenaswap": "ArenaSwap",
  "kryptodex": "KryptoDex",
  "bamboodefi": "BambooDeFi",
  "swapp": "SWAPP",
  "fortune-dao": "Fortune DAO",
  "aquarius": "Aquarius",
  "stacker-ventures": "Stacker Ventures",
  "dungeonswap": "DungeonSwap",
  "piggy": "Piggy",
  "stormswap": "StormSwap",
  "parrot-defi": "Parrot Defi",
  "defi-yield-protocol": "Defi Yield Protocol",
  "avalps": "Avalps",
  "gravity-finance": "Gravity Finance",
  "agarthadao": "AgarthaDAO",
  "spiritdao": "SpiritDAO",
  "1bch": "1BCH",
  "partyswap": "PartySwap",
  "treedefi": "TreeDefi",
  "neku": "Neku",
  "baker-guild": "Baker Guild",
  "genesys": "Genesys",
  "coffin-finance": "Coffin Finance",
  "moonswap": "Moonswap",
  "sunflowerswap": "SunflowerSwap",
  "pureswap": "PureSwap",
  "ruler": "Ruler",
  "zyxswap": "ZYXSwap",
  "flame-defi": "Flame DeFi",
  "smartdex": "SmartDEX",
  "basis-cash": "Basis Cash",
  "polydex-cryption-network": "PolyDEX-Cryption Network",
  "bananafarm": "BananaFarm",
  "sumswap": "SumSwap",
  "btc-proxy": "BTC Proxy",
  "stargate-finance": "Stargate Finance",
  "polkaex": "PolkaEx",
  "n3rd-finance": "N3RD Finance",
  "entropyfi": "Entropyfi",
  "value-liquid": "Value Liquid",
  "purefi": "PureFi",
  "aliensfarm": "AliensFarm",
  "ante-finance": "Ante Finance",
  "vortex-dao": "Vortex DAO",
  "banksy-farm": "Banksy Farm",
  "chickenswap": "ChickenSwap",
  "polywhale-finance": "Polywhale Finance",
  "dapp-account-dao": "Dapp Account DAO",
  "shiba-fantom": "Shiba Fantom",
  "pika-protocol": "Pika Protocol",
  "levinswap": "Levinswap",
  "loterra": "LoTerra",
  "acoconut": "ACoconut",
  "polygonfarm-finance": "PolygonFarm Finance",
  "vanilla": "Vanilla",
  "cakedao": "CakeDAO",
  "impossible-finance": "Impossible Finance",
  "koala-defi": "Koala Defi",
  "freeriver": "FreeRiver",
  "emiswap": "EmiSwap",
  "minmax-finance": "MinMax Finance",
  "sperax-usd": "Sperax USD",
  "sonicswap": "SonicSwap",
  "manifest": "Manifest",
  "gaj-finance": "Gaj Finance",
  "piratedao": "PirateDAO",
  "opendao": "OpenDAO",
  "kokomoswap": "KokomoSwap",
  "kokoswap": "KokoSwap",
  "whale-loans": "Whale Loans",
  "polyshield": "PolyShield",
  "zlot": "zLot",
  "securedao": "SecureDAO",
  "bt.finance": "BT.Finance",
  "miniswap": "MiniSwap",
  "yapeswap": "Yapeswap",
  "finnexus": "FinNexus",
  "kebab-finance": "Kebab Finance",
  "qian": "QIAN",
  "xdollar": "xDollar",
  "the-grand-banks": "The Grand Banks",
  "karma-dao": "Karma DAO",
  "zoomswap": "ZoomSwap",
  "tendieswap": "TendieSwap",
  "ubiquity-dao": "Ubiquity DAO",
  "deepseadao": "DeepSeaDAO",
  "complus-network": "Complus Network",
  "safedollar": "SafeDollar",
  "dark-matter": "Dark Matter",
  "twindex": "Twindex",
  "doki-doki-finance": "Doki Doki Finance",
  "meowswap": "Meowswap",
  "alium-swap": "Alium Swap",
  "retrodefi": "RetroDefi",
  "ice-colony": "Ice Colony",
  "liquidswap": "LiquidSwap",
  "salem-finance": "Salem Finance",
  "ifswap": "IFSwap",
  "yfdai": "YFDAI",
  "mama-dao": "Mama DAO",
  "kingdefi": "KingDefi",
  "merlin": "Merlin",
  "dino.exchange": "Dino.Exchange",
  "mean-finance": "Mean Finance",
  "governor-dao": "Governor DAO",
  "daoventures": "DAOventures",
  "dehive": "DeHive",
  "tornadao": "Tornadao",
  "mercurity": "Mercurity",
  "goswap": "GoSwap",
  "aperocket": "ApeRocket",
  "mensa-protocol": "Mensa Protocol",
  "cougarswap": "CougarSwap",
  "asgard-dao": "Asgard Dao",
  "thoreum-finance": "Thoreum Finance",
  "robiniaswap": "RobiniaSwap",
  "xmas-past": "Xmas Past",
  "behodler": "Behodler",
  "omicron": "Omicron",
  "mfinance": "MFinance",
  "senpaiswap": "SenpaiSwap",
  "arbicheems": "ArbiCheems",
  "hswap": "HSwap",
  "amy-finance": "Amy Finance",
  "meso-finance": "Meso Finance",
  "gondola-finance": "Gondola Finance",
  "s-finance": "S Finance",
  "ragnarokdao": "RagnarokDAO",
  "ara-finance": "Ara Finance",
  "talent-protocol": "Talent Protocol",
  "fluity": "Fluity",
  "frost-finance": "Frost Finance",
  "hpdex": "Hpdex",
  "polyyeld-finance": "PolyYeld Finance",
  "corgiswap": "CorgiSwap",
  "raven": "Raven",
  "arbirise-finance": "ArbiRise Finance",
  "taichi": "TaiChi",
  "vaulty-finance": "Vaulty Finance",
  "squid-stake": "Squid Stake",
  "bring.finance": "Bring.Finance",
  "cybertime": "CyberTime",
  "xensa": "Xensa",
  "kuu-finance": "Kuu Finance",
  "longdrink": "Longdrink",
  "swapmatic": "SwapMatic",
  "shadecash": "ShadeCash",
  "typhoon-cash": "Typhoon Cash",
  "reverse": "Reverse",
  "smolswap": "SmolSwap",
  "tinyman": "Tinyman",
  "xusd-money": "XUSD Money",
  "illuvium": "Illuvium",
  "westarter": "WeStarter",
  "8ightdao": "8ightDAO",
  "zabu-finance": "Zabu Finance",
  "union-finance": "Union Finance",
  "pumpkin-dao": "Pumpkin DAO",
  "grassland-finance": "GrassLand Finance",
  "polkamarkets": "Polkamarkets",
  "defirex": "Defirex",
  "dao-maker": "DAO Maker",
  "bourbon-dao": "Bourbon DAO",
  "cofix": "CoFiX",
  "r-u-generous": "R U Generous",
  "wraithswap": "WraithSwap",
  "borgswap": "BorgSwap",
  "spicy-dao": "Spicy DAO",
  "polyroll": "Polyroll",
  "elephantdex": "Elephantdex",
  "flashstake": "Flashstake",
  "draco-force": "Draco Force",
  "sapphire-defi": "Sapphire Defi",
  "fantompup": "FantomPup",
  "marshmallowdefi": "MarshmallowDeFi",
  "farm-hero": "Farm Hero",
  "blizzard": "Blizzard",
  "primitive": "Primitive",
  "risq-protocol": "Risq Protocol",
  "acumen": "Acumen",
  "brinc": "Brinc",
  "cerberusdao": "CerberusDAO",
  "vampireswap": "VampireSwap",
  "qilin": "Qilin",
  "helios-prime": "Helios Prime",
  "skeleton-finance": "Skeleton Finance",
  "brahma": "Brahma",
  "scarecrow-finance": "ScareCrow Finance",
  "valhalladao": "ValhallaDAO",
  "buffaloswap": "Buffaloswap",
  "monox": "MonoX",
  "carbon-finance": "Carbon Finance",
  "blackbird-finance": "BlackBird Finance",
  "cyberfantasyfembots": "CyberFantasyFembots",
  "cryptoyieldfocus": "CryptoYieldFocus",
  "cyber-dog": "Cyber Dog",
  "swing-dao": "Swing DAO",
  "the-seed-farm": "The Seed Farm",
  "thales": "Thales",
  "mintswap": "MintSwap",
  "dracula": "Dracula",
  "overnight": "Overnight",
  "zunami": "Zunami",
  "metacrono": "MetaCrono",
  "eggtartswap": "EggTartSwap",
  "adena-finance": "Adena Finance",
  "avaviking": "AvaViking",
  "pinyottas": "Pinyottas",
  "kimochi": "Kimochi",
  "zeus-finance": "Zeus Finance",
  "samodao": "SamoDAO",
  "squid-defi": "Squid-Defi",
  "genesis-finance": "Genesis Finance",
  "optinyan": "OptiNyan",
  "lemonswap": "LemonSwap",
  "firedao": "FireDAO",
  "bouje-finance": "Bouje Finance",
  "deerfi": "DeerFi",
  "robo-advisor-for-yield": "Robo-Advisor for Yield",
  "unirex-finance": "Unirex Finance",
  "jaguarswap": "JaguarSwap",
  "vultureswap": "VultureSwap",
  "emerald-swap": "Emerald Swap",
  "afraswap": "AfraSwap",
  "solana-farm": "Solana Farm",
  "the-dragons-lair": "The Dragon's Lair",
  "mirai": "Mirai",
  "caribou-finance": "Caribou Finance",
  "coup-farm": "Coup Farm",
  "bear-finance": "Bear Finance",
  "chad-finance": "Chad Finance",
  "defi-halal": "Defi Halal",
  "tomofinance": "TomoFinance",
  "bitant": "BitANT",
  "babypig-finance": "BabyPig Finance",
  "ftm-frens": "FTM Frens",
  "moondao": "MoonDao",
  "hotpot-finance": "Hotpot Finance",
  "tenet": "Tenet",
  "hermes-defi": "Hermes Defi",
  "sunflower-finance": "SunFlower Finance",
  "amogus-dao": "Amogus DAO",
  "nowswap": "NowSwap",
  "undead-finance": "Undead Finance",
  "snowdog": "Snowdog",
  "asgard-finance": "Asgard Finance",
  "nidhi-dao": "Nidhi-Dao",
  "bepswap": "Bepswap",
  "synlev": "SynLev",
  "tomb-finance": "Tomb Finance",
  "telcoin": "Telcoin",
  "avalaunch": "Avalaunch",
  "nuls": "Nuls",
  "sunrise-gaming": "Sunrise Gaming",
  "coinswap-space": "Coinswap Space",
  "babyswap": "BabySwap",
  "shapeshift": "ShapeShift",
  "banano": "Banano",
  "bogged-finance": "Bogged Finance",
  "totemfi": "TotemFi",
  "sync-network": "SYNC Network",
  "only1": "Only1",
  "swap-cat": "Swap Cat",
  "fegex": "Fegex",
  "oraichain": "OraiChain",
  "bacondao": "BaconDAO",
  "yel-finance": "YEL Finance",
  "smartcoin": "SmartCoin",
  "billion-happiness": "Billion Happiness",
  "decubate": "Decubate",
  "nasdex": "Nasdex",
  "atmossoft": "AtmosSoft",
  "zigzag": "ZigZag",
  "capital-dao": "Capital DAO",
  "nest-protocol": "Nest Protocol",
  "axedao": "AxeDAO",
  "saffron-finance": "Saffron Finance",
  "safeohm": "SafeOHM",
  "paraswap": "Paraswap",
  "blackpool": "BlackPool",
  "everestdao": "EverestDAO",
  "radao": "RaDao",
  "hex": "Hex",
  "freeliquid": "FreeLiquid",
  "arcx": "ARCx",
  "alpaca-city": "Alpaca City",
  "retreeb": "Retreeb",
  "zai-finance": "Zai Finance",
  "honeyfarm": "HoneyFarm",
  "giza-dao": "Giza DAO",
  "colony": "Colony",
  "tempodao": "TempoDAO",
  "rivrkitty": "RivrKitty",
  "base-protocol": "Base Protocol",
  "bitpif": "BITPIF",
  "numbers-protocol": "Numbers Protocol",
  "merit-circle": "Merit Circle",
  "mobox": "MOBOX",
  "sheesha-finance": "Sheesha Finance",
  "the-sandbox": "The Sandbox",
  "brokoli-network": "Brokoli Network",
  "nacho-finance": "Nacho Finance",
  "kitty-finance": "Kitty Finance",
  "polkastarter": "Polkastarter",
  "everipedia": "Everipedia",
  "zodiacdao": "ZodiacDAO",
  "one-cash": "One Cash",
  "stand-cash": "Stand Cash",
  "optidoge": "Optidoge",
  "snowcatdao": "SnowCatDAO",
  "wisteria-swap": "Wisteria Swap",
  "louverture": "Louverture",
  "kawaiiswap": "KawaiiSwap",
  "valkyrie": "Valkyrie",
  "umbrella-network": "Umbrella Network",
  "cyclos": "Cyclos",
  "unite-finance": "Unite Finance",
  "piggy-finance": "Piggy Finance",
  "scarab-finance": "Scarab Finance",
  "rarify": "Rarify",
  "galatea-cash": "Galatea Cash",
  "instrumental-finance": "Instrumental Finance",
  "chikn-farm": "Chikn Farm",
  "chronicle": "Chronicle",
  "ferrum": "Ferrum",
  "predictcoin": "Predictcoin",
  "voyager": "Voyager",
  "ovr": "OVR"
}
