{
    "OPENBB_PACKAGED_APPLICATION": "True",
    "OPENBB_LOGGING_COMMIT_HASH": "sha:b171083f",
    "OPENBB_ENABLE_PREDICT": "True",
    "OPENBB_ENABLE_CHECK_API": "True",
    "OPENBB_ENABLE_THOUGHTS_DAY": "False",
    "OPENBB_REMEMBER_CONTEXTS": "True",
    "OPENBB_USE_FLAIR": ":openbb",
    "OPENBB_USE_WATERMARK": "True",
    "OPENBB_USE_CMD_LOCATION_FIGURE": "True",
    "OPENBB_USE_PROMPT_TOOLKIT": "True",
    "OPENBB_USE_COLOR": "True",
    "OPENBB_USE_ION": "True",
    "OPENBB_USE_PLOT_AUTOSCALING": "False",
    "OPENBB_ENABLE_RICH": "True",
    "OPENBB_ENABLE_RICH_PANEL": "True",
    "OPENBB_MPLSTYLE": "dark",
    "OPENBB_MPFSTYLE": "dark",
    "OPENBB_RICHSTYLE": "dark",
    "OPENBB_LOGGING_VERBOSITY": "0",
    "OPENBB_DEBUG_MODE": "False",
    "OPENBB_LOG_COLLECTION": "False",
    "OPENBB_ONLY_SEND_FILE_SIZE": "False",
    "OPENBB_USE_TABULATE_DF": "True",
    "OPENBB_USE_CLEAR_AFTER_CMD": "False",
    "OPENBB_USE_DATETIME": "True",
    "OPENBB_OPEN_REPORT_AS_HTML": "True",
    "OPENBB_ENABLE_QUICK_EXIT": "False",
    "OPENBB_ENABLE_EXIT_AUTO_HELP": "False",
    "OBBFF_LOGGING_COMMIT_HASH": "sha:26c03c7c"
}